brutefit/__init__.py
brutefit/bayesfactor.py
brutefit/core.py
brutefit/plot.py
brutefit/stats.py
brutefit/sympy.py
brutefit/transform.py
brutefit/utils.py
brutefit-0.2.2.dist-info/METADATA
brutefit-0.2.2.dist-info/WHEEL
brutefit-0.2.2.dist-info/top_level.txt
brutefit-0.2.2.dist-info/zip-safe
brutefit-0.2.2.dist-info/RECORD
