Metadata-Version: 2.1
Name: brutefit
Version: 0.2.2
Summary: Tools for finding an arbitrary multivariate polynomial that best fits some data.
Home-page: https://github.com/oscarbranson/brutefit
Author: Oscar Branson
Author-email: ob266@cam.ac.uk
License: MIT
Keywords: science
Classifier: Programming Language :: Python :: 3 :: Only
Classifier: Intended Audience :: Science/Research
Requires-Dist: numpy (>=1.13)
Requires-Dist: scikit-learn (>=0.18)
Requires-Dist: pandas (>=0.19)
Requires-Dist: sympy
Requires-Dist: tqdm (>=4.14)
